CHANGES.txt
LICENSE.txt
MANIFEST.in
README.txt
setup.py
js/__init__.py
js.jquery_slimbox.egg-info/PKG-INFO
js.jquery_slimbox.egg-info/SOURCES.txt
js.jquery_slimbox.egg-info/dependency_links.txt
js.jquery_slimbox.egg-info/entry_points.txt
js.jquery_slimbox.egg-info/namespace_packages.txt
js.jquery_slimbox.egg-info/not-zip-safe
js.jquery_slimbox.egg-info/requires.txt
js.jquery_slimbox.egg-info/top_level.txt
js/jquery_slimbox/__init__.py
js/jquery_slimbox/test_slimbox.txt
js/jquery_slimbox/resources/css/closelabel.gif
js/jquery_slimbox/resources/css/loading.gif
js/jquery_slimbox/resources/css/nextlabel.gif
js/jquery_slimbox/resources/css/prevlabel.gif
js/jquery_slimbox/resources/css/slimbox2-rtl.css
js/jquery_slimbox/resources/css/slimbox2.css
js/jquery_slimbox/resources/extra/android-market.js
js/jquery_slimbox/resources/extra/autoactivation.js
js/jquery_slimbox/resources/extra/fix-urls.js
js/jquery_slimbox/resources/extra/flickr.js
js/jquery_slimbox/resources/extra/picasaweb.js
js/jquery_slimbox/resources/js/slimbox2.js
js/jquery_slimbox/resources/src/autoload.js
js/jquery_slimbox/resources/src/slimbox2.js