Metadata-Version: 1.0
Name: js.jquery-slimbox
Version: 2.04-1
Summary: Fanstatic packaging of Slimbox
Home-page: UNKNOWN
Author: Fanstatic Developers
Author-email: fanstatic@googlegroups.com
License: BSD
Platform: UNKNOWN
